discretelog/__init__.py
discretelog/__main__.py
discretelog/block_lanczos.py
discretelog/common.py
discretelog/linear_sieve_index_calculus.py
discretelog/naive_index_calculus.py
discretelog/utils.py
discretelog-0.1.1.dist-info/LICENSE
discretelog-0.1.1.dist-info/METADATA
discretelog-0.1.1.dist-info/WHEEL
discretelog-0.1.1.dist-info/RECORD
