Metadata-Version: 2.1
Name: discretelog
Version: 0.1.1
Summary: Discrete logarithms in the ring of integers modulo n
Home-page: https://github.com/gilcu3/discretelog
License: Apache Software License 2.0
Keywords: discrete logarithm,number theory,cryptography
Author: gilcu3
Requires-Python: >=3.10,<4.0
Classifier: Development Status :: 3 - Alpha
Classifier: Environment :: Console
Classifier: Intended Audience :: Education
Classifier: Intended Audience :: Science/Research
Classifier: License :: OSI Approved :: Apache Software License
Classifier: License :: Other/Proprietary License
Classifier: Operating System :: OS Independent
Classifier: Programming Language :: Python :: 3
Classifier: Programming Language :: Python :: 3.10
Classifier: Programming Language :: Python :: 3.11
Classifier: Programming Language :: Python :: 3.12
Classifier: Topic :: Scientific/Engineering :: Mathematics
Classifier: Topic :: Software Development :: Libraries :: Python Modules
Classifier: Topic :: Utilities
Requires-Dist: colorama (>=0.4.6,<0.5.0)
Requires-Dist: primefac (>=2.0.12,<3.0.0)
Requires-Dist: tqdm (>=4.66.4,<5.0.0)
Project-URL: Repository, https://github.com/gilcu3/discretelog
